AUTHORS.txt
Dockerfile
LICENSE.txt
MANIFEST.in
NEWS.rst
README.rst
requirements.txt
setup.py
TimeSide.egg-info/PKG-INFO
TimeSide.egg-info/SOURCES.txt
TimeSide.egg-info/dependency_links.txt
TimeSide.egg-info/not-zip-safe
TimeSide.egg-info/requires.txt
TimeSide.egg-info/top_level.txt
doc/Makefile
doc/build.sh
doc/make.bat
doc/images/TimeSide_pipe.svg
doc/images/timeside_player_01.png
doc/images/timeside_schema.dia
doc/images/timeside_schema.svg
doc/ipynb/01_Timeside_API.ipynb
doc/ipynb/02_Aubio.ipynb
doc/source/architecture.rst
doc/source/conf.py
doc/source/copyright.rst
doc/source/development.rst
doc/source/divein.rst
doc/source/doc.rst
doc/source/index.rst
doc/source/install.rst
doc/source/intro.rst
doc/source/news.rst
doc/source/processors.rst
doc/source/production.rst
doc/source/related.rst
doc/source/ui.rst
doc/source/api/index.rst
doc/source/api/analyzer/analyzers.rst
doc/source/api/analyzer/core.rst
doc/source/api/analyzer/core_analyzers.rst
doc/source/api/analyzer/ext_analyzers.rst
doc/source/api/analyzer/index.rst
doc/source/api/analyzer/preprocessors.rst
doc/source/api/decoder/index.rst
doc/source/api/encoder/index.rst
doc/source/api/grapher/index.rst
doc/source/api/server/index.rst
doc/source/tutorials/data_management.rst
doc/source/tutorials/frames_stack.rst
doc/source/tutorials/index.rst
doc/source/tutorials/quick_start.rst
doc/source/tutorials/streaming.rst
scripts/timeside-launch
scripts/timeside-waveforms
scripts/presets/draw_waveform_contour_white.ts
scripts/presets/extract_aubio_bpm.ts
scripts/presets/transcode_media.ts
tests/run_all_tests
tests/test_AnalyzerResult.py
tests/test_AnalyzerResult_factory.py
tests/test_analyzer_dc.py
tests/test_analyzer_level.py
tests/test_analyzer_preprocessors.py
tests/test_analyzers_default.py
tests/test_analyzers_stress.py
tests/test_array_decoding.py
tests/test_aubio_melenergy.py
tests/test_aubio_mfcc.py
tests/test_aubio_pitch.py
tests/test_aubio_specdesc.py
tests/test_aubio_temporal.py
tests/test_check_processors.py
tests/test_component.py
tests/test_core_processors.py
tests/test_decoder_utils.py
tests/test_decoding.py
tests/test_decoding_stack.py
tests/test_encoding.py
