Metadata-Version: 1.1
Name: TimeSide
Version: 0.8
Summary: open web audio processing framework
Home-page: https://github.com/Parisson/TimeSide/
Author: Guillaume Pellerin, Paul Brossier, Thomas Fillon, Riccardo Zaccarelli, Olivier Guilyardi
Author-email: yomguy@parisson.com, piem@piem.org, thomas@parisson.com, riccardo.zaccarelli@gmail.com, olivier@samalyse.com
License: Gnu Public License V2
Keywords: audio analysis features extraction MIR transcoding graph visualize plot HTML5 interactive metadata player
Platform: OS Independent
Classifier: Intended Audience :: Science/Research
Classifier: Intended Audience :: Developers
Classifier: Intended Audience :: Information Technology
Classifier: Programming Language :: Python
Classifier: Programming Language :: JavaScript
Classifier: Topic :: Internet :: WWW/HTTP :: Dynamic Content
Classifier: Topic :: Multimedia :: Sound/Audio
Classifier: Topic :: Multimedia :: Sound/Audio :: Analysis
Classifier: Topic :: Multimedia :: Sound/Audio :: Players
Classifier: Topic :: Multimedia :: Sound/Audio :: Conversion
Classifier: Topic :: Scientific/Engineering :: Information Analysis
Classifier: Topic :: Software Development :: Libraries :: Python Modules
